Metadata-Version: 2.1
Name: discord.py-self-embed
Version: 1.0.7
Summary: A way for selfbots to send embeds again.
Home-page: https://github.com/bentettmar/discord.py-self_embed
Download-URL: https://github.com/bentettmar/discord.py-self_embed/archive/refs/tags/1.0.6.tar.gz
Author: Ben Tettmar
Author-email: hello@benny.fun
License: MIT
Keywords: discord,embed,selfbot,discord embed,embed discord,discord selfbot embed,embed selfbot discord
Classifier: Development Status :: 5 - Production/Stable
Classifier: Intended Audience :: Developers
Classifier: License :: OSI Approved :: MIT License
Classifier: Programming Language :: Python :: 3.6
Classifier: Programming Language :: Python :: 3.7
Classifier: Programming Language :: Python :: 3.8
Classifier: Programming Language :: Python :: 3.9
Classifier: Programming Language :: Python :: 3.10
License-File: LICENSE
